fswatch/__init__.py
fswatch/fswatch.py
fswatch/libfswatch.py
fswatch-0.1.1.dist-info/LICENSE
fswatch-0.1.1.dist-info/WHEEL
fswatch-0.1.1.dist-info/METADATA
fswatch-0.1.1.dist-info/RECORD
