Metadata-Version: 2.1
Name: fswatch
Version: 0.1.1
Summary: Python wrapper for the libfswatch
Home-page: https://github.com/paul-nameless/pyfswatch
License: MIT
Author: Paul Nameless
Author-email: klym.paul@gmail.com
Requires-Python: >=3.5
Classifier: Programming Language :: Python :: 3
